brickfront/__init__.py
brickfront/_build.py
brickfront/build.py
brickfront/client.py
brickfront/errors.py
brickfront/review.py
brickfront/theme.py
brickfront-0.0.5.dist-info/DESCRIPTION.rst
brickfront-0.0.5.dist-info/METADATA
brickfront-0.0.5.dist-info/RECORD
brickfront-0.0.5.dist-info/WHEEL
brickfront-0.0.5.dist-info/metadata.json
brickfront-0.0.5.dist-info/top_level.txt
