Metadata-Version: 2.0
Name: brickfront
Version: 0.0.5
Summary: A wrapper for Brickset written in Python.
Home-page: https://github.com/4Kaylum/Brickfront
Author: Callum Bartlett
Author-email: callum.b@techie.com
License: mit
Download-URL: https://github.com/4Kaylum/Brickfront/tarball/0.0.5
Keywords: lego web brickset
Platform: UNKNOWN
Classifier: Development Status :: 3 - Alpha
Classifier: Intended Audience :: Developers
Classifier: Topic :: Games/Entertainment
Classifier: Topic :: Internet
Classifier: Topic :: Utilities
Classifier: License :: OSI Approved :: MIT License
Classifier: Programming Language :: Python :: 2
Classifier: Programming Language :: Python :: 3
Requires-Dist: requests
